{
    "meta": {
        "name": "DJI Mavic 3 Pro (DJI-RC)",
        "product_id": "151755777",
        "opinion_count": 2,
        "image": "https://image.ceneostatic.pl/data/products/151755777/f-dji-mavic-3-pro-dji-rc.jpg",
        "average_score": 0.95
    },
    "content": [
        {
            "opinionId": "18383407",
            "author": "s...p",
            "recommendation": true,
            "score": 1.0,
            "content": "Najlepszy w swojej klasie.",
            "pros": null,
            "cons": null,
            "helpful": 0,
            "unhelpful": 0,
            "publishDate": "2024-02-09 09:13:03",
            "purchaseDate": "2023-09-13 19:40:54"
        },
        {
            "opinionId": "18287681",
            "author": "v...b",
            "recommendation": true,
            "score": 0.9,
            "content": "🫶",
            "pros": null,
            "cons": null,
            "helpful": 0,
            "unhelpful": 0,
            "publishDate": "2024-01-10 08:45:37",
            "purchaseDate": "2023-12-19 19:04:04"
        }
    ]
}